{"target":[{"rank":1,"userName":"FDZ","huntingCount":0,"playMilliSecondTime":9362},{"rank":2,"userName":"BFD","huntingCount":0,"playMilliSecondTime":10654},{"rank":3,"userName":"DAA","huntingCount":2,"playMilliSecondTime":14062},{"rank":4,"userName":"FDA","huntingCount":4,"playMilliSecondTime":20663},{"rank":5,"userName":"GCT","huntingCount":12,"playMilliSecondTime":22001},{"rank":6,"userName":"ASG","huntingCount":12,"playMilliSecondTime":22001},{"rank":7,"userName":"FVD","huntingCount":9,"playMilliSecondTime":35440},{"rank":8,"userName":"DFA","huntingCount":15,"playMilliSecondTime":69539}]}